{
  "migrations": [
    {
      "version": "13.9.0-beta.0",
      "description": "Replace @nrwl/tao with nx",
      "cli": "nx",
      "implementation": "./src/migrations/update-13-9-0/replace-tao-with-nx",
      "package": "@nrwl/workspace",
      "name": "13-9-0-replace-tao-with-nx"
    },
    {
      "version": "13.10.0-beta.0",
      "description": "Update the decorate-angular-cli script to require nx instead of @nrwl/cli",
      "cli": "nx",
      "implementation": "./src/migrations/update-13-10-0/update-decorate-cli",
      "package": "@nrwl/workspace",
      "name": "13-10-0-update-decorate-cli"
    },
    {
      "version": "13.10.0-beta.0",
      "description": "Update the tasks runner property to import it from the nx package instead of @nrwl/worksapce",
      "cli": "nx",
      "implementation": "./src/migrations/update-13-10-0/update-tasks-runner",
      "package": "@nrwl/workspace",
      "name": "13-10-0-update-tasks-runner"
    },
    {
      "cli": "nx",
      "version": "13.8.4",
      "description": "Karma coverage is broken since Angular 13 upgarde and the karma config is severely out of date. Bring it up to date fixing the coverage issue.",
      "factory": "./src/migrations/update-13-8-4/migrate-karma-conf",
      "package": "@nrwl/angular",
      "name": "migrate-karma-config"
    },
    {
      "cli": "nx",
      "version": "13.9.0-beta.4",
      "description": "Set buildLibsFromSource property to false to not break existing usage.",
      "factory": "./src/migrations/update-13-9-0/set-build-libs-from-source",
      "package": "@nrwl/angular",
      "name": "set-build-libs-from-source"
    },
    {
      "cli": "nx",
      "version": "13.8.5-beta.1",
      "description": "Renames @nrwl/js:node to @nrwl/node:node",
      "factory": "./src/migrations/update-13-8-5/update-node-executor",
      "package": "@nrwl/js",
      "name": "update-node-executor"
    },
    {
      "cli": "nx",
      "version": "13.8.5-beta.1",
      "description": "Adjust .swcrc to .lib.swcrc",
      "factory": "./src/migrations/update-13-8-5/update-swcrc",
      "package": "@nrwl/js",
      "name": "update-swcrc"
    },
    {
      "cli": "nx",
      "version": "13.8.5-beta.1",
      "description": "Renames @nrwl/node:build to @nrwl/node:webpack",
      "factory": "./src/migrations/update-13-8-5/rename-build-to-webpack",
      "package": "@nrwl/node",
      "name": "rename-build-to-webpack"
    },
    {
      "cli": "nx",
      "version": "13.8.5-beta.1",
      "description": "Renames @nrwl/node:execute to @nrwl/node:node",
      "factory": "./src/migrations/update-13-8-5/rename-execute-to-node",
      "package": "@nrwl/node",
      "name": "rename-execute-to-node"
    },
    {
      "cli": "nx",
      "version": "13.8.5-beta.1",
      "description": "Renames @nrwl/node:package to @nrwl/js:tsc",
      "factory": "./src/migrations/update-13-8-5/update-package-to-tsc",
      "package": "@nrwl/node",
      "name": "update-package-to-tsc"
    },
    {
      "cli": "nx",
      "version": "13.10.0-beta.0",
      "description": "Update to React 18",
      "factory": "./src/migrations/update-13-10-0/update-13-10-0",
      "package": "@nrwl/react",
      "name": "update-react-18-13.10.0"
    }
  ]
}
